bundle_submission/__init__.py
bundle_submission/bundle.py
submission_bundler-0.1.0.dist-info/LICENSE
submission_bundler-0.1.0.dist-info/WHEEL
submission_bundler-0.1.0.dist-info/METADATA
submission_bundler-0.1.0.dist-info/RECORD
