Metadata-Version: 2.1
Name: submission-bundler
Version: 0.1.0
Summary: A package to bundle and generate submission file for competitive-programming. 
Author: Hiroshi Tsuyuki
Author-email: kagemeka1@gmail.com
Requires-Python: >=3.9,<3.10
Classifier: Programming Language :: Python :: 3
Classifier: Programming Language :: Python :: 3.9
